nonebot_plugin_markdown2img/__init__.py
nonebot_plugin_markdown2img/config.py
nonebot_plugin_markdown2img/renderer.py
nonebot_plugin_markdown2img-0.0.3.dist-info/WHEEL
nonebot_plugin_markdown2img-0.0.3.dist-info/METADATA
nonebot_plugin_markdown2img-0.0.3.dist-info/RECORD
