Metadata-Version: 2.3
Name: nonebot-plugin-markdown2img
Version: 0.0.3
Summary: 可作为函数调用的Markdown渲染图片插件
Author: ANGJustinl
Author-email: ANGJustinl <angjustinl@gmail.com>
Requires-Dist: nonebot2>=2.4.3,<3.0.0
Requires-Dist: nonebot-adapter-onebot>=2.4.6,<3.0.0
Requires-Dist: markdown-it-py>=4.0.0
Requires-Dist: mdit-py-plugins>=0.5.0
Requires-Dist: html2image>=2.0.7
Requires-Dist: pygments>=2.19.2
Requires-Dist: linkify-it-py>=2.0.3
Requires-Dist: pillow>=12.0.0
Requires-Python: >=3.10
Project-URL: Homepage, https://github.com/ANGJustinl/nonebot_plugin_markdown2img
Project-URL: Issues, https://github.com/ANGJustinl/nonebot_plugin_markdown2img/issues
Project-URL: Repository, https://github.com/ANGJustinl/nonebot_plugin_markdown2img.git
